shortzyy/__init__.py
shortzyy/main.py
shortzyy-0.0.6.dist-info/LICENSE
shortzyy-0.0.6.dist-info/METADATA
shortzyy-0.0.6.dist-info/WHEEL
shortzyy-0.0.6.dist-info/top_level.txt
shortzyy-0.0.6.dist-info/RECORD
